LICENSE
MANIFEST.in
README.rst
setup.py
statico/__init__.py
statico/__main__.py
statico/contents.py
statico/generators.py
statico/helpers.py
statico/pylog.py
statico/readers.py
statico/statico.py
statico/tasks.py
statico/utils.py
statico/watcher.py
statico.egg-info/PKG-INFO
statico.egg-info/SOURCES.txt
statico.egg-info/dependency_links.txt
statico.egg-info/entry_points.txt
statico.egg-info/pbr.json
statico.egg-info/requires.txt
statico.egg-info/top_level.txt
statico/data/atom.xml
statico/data/settings.json
statico/data/static/css/main.css
statico/data/static/css/normalize.css
statico/data/static/css/paginator.css
statico/data/static/css/pygments.css
statico/data/static/images/favicon.png
statico/data/static/js/main.js
statico/data/static/js/paginator.min.js
statico/data/templates/article.html
statico/data/templates/base.html
statico/data/templates/category.html
statico/data/templates/default.html
statico/data/templates/page.html
statico/data/templates/includes/after_footer.html
statico/data/templates/includes/footer.html
statico/data/templates/includes/head.html
statico/data/templates/includes/header.html
statico/data/templates/includes/navigation.html
statico/data/templates/includes/asides/github.html
statico/data/templates/includes/asides/recent_posts.html